{
  "Revision": "RELEASE5",
  "Inherit": "RELEASE3",
  "Capabilities": {
    "PACKET_LENGTH_BASE128_PREFIXED": true,
    "PACKET_LENGTH_STRING_PREFIXED": false
  },
  "Incoming": {},
  "Outgoing": {
    "Handshake.AuthenticationOK": {
      "Id": "OK",
      "Structure": []
    },
    "Handshake.UserObject": {
      "Id": "USEROBJECT",
      "Structure": [
        {
          "Mapping": "Field",
          "Type": "text:name",
          "Name": "Username"
        },
        {
          "Mapping": "Field",
          "Type": "text:figure",
          "Name": "Classic(Figure)"
        },
        {
          "Mapping": "Field",
          "Type": "text:sex",
          "Name": "Gender"
        },
        {
          "Mapping": "Field",
          "Type": "text:customData",
          "Name": "CustomData"
        },
        {
          "Mapping": "Field",
          "Type": "text:ph_tickets",
          "Name": "Tickets"
        },
        {
          "Mapping": "Field",
          "Type": "text:photo_film",
          "Name": "Film"
        }
      ]
    }
  },
  "Structures": {},
  "Interfaces": {}
}